httpscraper.py
http_scraper-0.0.1.dist-info/LICENSE.txt
http_scraper-0.0.1.dist-info/METADATA
http_scraper-0.0.1.dist-info/WHEEL
http_scraper-0.0.1.dist-info/top_level.txt
http_scraper-0.0.1.dist-info/RECORD
