Metadata-Version: 2.2
Name: Http_scraper
Version: 0.0.1
Summary: A https scraper
Author-email: MarkMalunov <markmalunov@gmail.com>
License: MIT License
Classifier: Programming Language :: Python :: 3
Classifier: Operating System :: OS Independent
Requires-Python: >=3.10
License-File: LICENSE.txt
Requires-Dist: requests>=2.32.3
Requires-Dist: pandas>=2.2.3
Requires-Dist: beautifulsoup4>=4.13.3
